auditor_htcondor_collector/__init__.py
auditor_htcondor_collector/cli.py
auditor_htcondor_collector/collector.py
auditor_htcondor_collector/config.py
auditor_htcondor_collector/custom_types.py
auditor_htcondor_collector/exceptions.py
auditor_htcondor_collector/main.py
auditor_htcondor_collector/state_db.py
auditor_htcondor_collector/utils.py
auditor_htcondor_collector-0.10.0.dist-info/METADATA
auditor_htcondor_collector-0.10.0.dist-info/WHEEL
auditor_htcondor_collector-0.10.0.dist-info/entry_points.txt
auditor_htcondor_collector-0.10.0.dist-info/top_level.txt
auditor_htcondor_collector-0.10.0.dist-info/RECORD
