Metadata-Version: 2.4
Name: auditor-htcondor-collector
Version: 0.10.0
Summary: AUDITOR collector for aggregating data from the HTCondor batch system
Project-URL: documentation, https://alu-schumacher.github.io/AUDITOR/#htcondor-collector
Requires-Python: >=3.9
Requires-Dist: pyyaml==6.0.2
Requires-Dist: python-auditor==0.10.0
Provides-Extra: build
Requires-Dist: build==1.3.0; extra == "build"
Requires-Dist: setuptools==80.9.0; extra == "build"
